{
    "reactions": [
        {
            "monomers": [
                "monomer1",
                "styrene",
                "monomer2",
                "methyl acrylate"
            ],
            "reaction_conditions": [
                {
                    "polymerization_type": "atom transfer radical polymerization",
                    "solvent": "tetrahydrofuran",
                    "method": "bulk",
                    "temperature": 90.0,
                    "temperature_unit": "\u00b0C",
                    "reaction_constants": {
                        "constant_1": 1.018,
                        "constant_2": 0.177
                    },
                    "reaction_constant_conf": {
                        "constant_conf_1": 0.06,
                        "constant_conf_2": 0.025
                    },
                    "determination_method": "extended Kelen-Tudor",
                    "Q-value": {
                        "constant_1": "na",
                        "constant_2": "na"
                    },
                    "e-Value": {
                        "constant_1": "na",
                        "constant_2": "na"
                    },
                    "r_product": null
                },
                {
                    "polymerization_type": "atom transfer radical polymerization",
                    "solvent": "tetrahydrofuran",
                    "method": "bulk",
                    "temperature": 90.0,
                    "temperature_unit": "\u00b0C",
                    "reaction_constants": {
                        "constant_1": 1.016,
                        "constant_2": 0.179
                    },
                    "reaction_constant_conf": {
                        "constant_conf_1": 0.053,
                        "constant_conf_2": 0.023
                    },
                    "determination_method": "Mao-Huglin",
                    "Q-value": {
                        "constant_1": "na",
                        "constant_2": "na"
                    },
                    "e-Value": {
                        "constant_1": "na",
                        "constant_2": "na"
                    },
                    "r_product": null
                }
            ]
        }
    ],
    "source": "https://doi.org/10.1002/app.30804",
    "PDF_name": "Atom Transfer Radical Homo- and Copolymerization of Styrene and Methyl Acrylate Initiated with Trichloromethyl-Terminated Poly(vinyl acetate) Macroinitiator: A Kinetic Study"
}