{
    "file": "paper_431.json",
    "monomer1_s": "C=C(Cl)C(=O)OCC",
    "monomer2_s": "C=C(OC)C(=O)OC",
    "monomer1": "Ethyl alpha-Chloroacrylate",
    "monomer2": "Methyl alpha-Methoxyacrylate",
    "r_values": {
        "constant_1": 0.58,
        "constant_2": 0.11
    },
    "conf_intervals": {
        "constant_conf_1": null,
        "constant_conf_2": null
    },
    "temperature": 30.0,
    "temperature_unit": "\u00b0C",
    "solvent": "ClCCCl",
    "method": "bulk",
    "r-product": null,
    "source": "http://dx.doi.org/10.1080/00222338308081082",
    "logP": 1.464
}