{
    "file": "paper_226.json",
    "monomer1_s": "C=C(C)C(=O)OC",
    "monomer2_s": "C=C(C)C(=O)OC(C)C",
    "monomer1": "methyl methacrylate",
    "monomer2": "isopropyl methacrylate",
    "r_values": {
        "constant_1": 0.89,
        "constant_2": 1.2
    },
    "conf_intervals": {
        "constant_conf_1": 0.21,
        "constant_conf_2": 0.2
    },
    "temperature": 60.0,
    "temperature_unit": "\u00b0C",
    "solvent": "c1ccccc1",
    "method": "solvent",
    "r-product": null,
    "source": "https://doi.org/10.1002/pol.1968.160060607",
    "logP": 1.6866
}