{
    "file": "paper_77.json",
    "monomer1_s": "C=C(C)C(=O)Oc1ccccc1C(=O)O",
    "monomer2_s": "C=C(C)C(=O)OC",
    "monomer1": "ortho-methacryloyloxybenzoic acid",
    "monomer2": "methyl methacrylate",
    "r_values": {
        "constant_1": 1.22,
        "constant_2": 0.74
    },
    "conf_intervals": {
        "constant_conf_1": 0.05,
        "constant_conf_2": 0.05
    },
    "temperature": 60.0,
    "temperature_unit": "\u00b0C",
    "solvent": "CC(C)=O",
    "method": "solvent",
    "r-product": 0.9,
    "source": "https://doi.org/10.1016/0032-3861(87)90305-3",
    "logP": 0.5952999999999999
}